Workbook

Sheet Raw_Data
A1: Transaction_ID | B1: Date | C1: Region | D1: Product | E1: Customer_Segment | F1: Sales_Channel | G1: Units_Sold | H1: Unit_Price | I1: Revenue | J1: Cost
A2: 1 | B2: 45297 | C2: EU | D2: Training | E2: SMB | F2: Direct | G2: 152 | H2: 173.19 | I2: 26324.88 | J2: 12843.41
A3: 2 | B3: 45302 | C3: EU | D3: Software | E3: SMB | F3: Partner | G3: 122 | H3: 399.65 | I3: 48757.3 | J3: 19302.84
A4: 3 | B4: 45304 | C4: UK | D4: Software | E4: Mid-Market | F4: Online | G4: 175 | H4: 439.79 | I4: 76963.25 | J4: 30325.14
A5: 4 | B5: 45308 | C5: APAC | D5: Software | E5: Mid-Market | F5: Direct | G5: 157 | H5: 423.5 | I5: 66489.5 | J5: 27182.54
A6: 5 | B6: 45308 | C6: UK | D6: Hardware | E6: Mid-Market | F6: Direct | G6: 163 | H6: 532.96 | I6: 86872.48 | J6: 57527.97
A7: 6 | B7: 45310 | C7: UK | D7: Software | E7: Mid-Market | F7: Partner | G7: 189 | H7: 437.94 | I7: 82770.66 | J7: 36462.12
A8: 7 | B8: 45316 | C8: APAC | D8: Hardware | E8: Enterprise | F8: Direct | G8: 218 | H8: 606.71 | I8: 132262.78 | J8: 92675.07
A9: 8 | B9: 45316 | C9: US | D9: Training | E9: Enterprise | F9: Online | G9: 129 | H9: 281.49 | I9: 36312.21 | J9: 18653.99
A10: 9 | B10: 45319 | C10: APAC | D10: Services | E10: Enterprise | F10: Direct | G10: 140 | H10: 372.97 | I10: 52215.8 | J10: 30417.33
A11: 10 | B11: 45322 | C11: US | D11: Hardware | E11: Enterprise | F11: Online | G11: 142 | H11: 778.96 | I11: 110612.32 | J11: 75178.03
A12: 11 | B12: 45325 | C12: US | D12: Training | E12: SMB | F12: Direct | G12: 202 | H12: 218.22 | I12: 44080.44 | J12: 21690.37
A13: 12 | B13: 45331 | C13: US | D13: Training | E13: Enterprise | F13: Direct | G13: 133 | H13: 292.07 | I13: 38845.31 | J13: 19022.93
... A289: 288 | B289: 46159 | C289: US | D289: Training | E289: Public Sector | F289: Partner | G289: 22 | H289: 240.21 | I289: 5284.62 | J289: 2454.19

Sheet Data_Cleaning
A1: Transaction_ID | B1: Date | C1: Region | D1: Product | E1: Customer_Segment | F1: Sales_Channel | G1: Units_Sold | H1: Unit_Price | I1: Revenue | J1: Cost | K1: Month | L1: Quarter | M1: Profit | N1: Profit_Margin
A2: =Raw_Data!A2 -> 1 | B2: =Raw_Data!B2 -> 45297 | C2: =Raw_Data!C2 -> EU | D2: =Raw_Data!D2 -> Training | E2: =Raw_Data!E2 -> SMB | F2: =Raw_Data!F2 -> Direct | G2: =Raw_Data!G2 -> 152 | H2: =Raw_Data!H2 -> 173.19 | ... J2: =Raw_Data!J2 -> 12843.41 | K2: =TEXT(B2,"yyyy-mm") -> 2024-01 | L2: ="Q"&ROUNDUP(MONTH(B2)/3,0)&"-"&YEAR(B2) -> Q1-2024 | M2: =I2-J2 -> 13481.47 | N2: =IFERROR(M2/I2,0) -> 0.51211895
A3: =Raw_Data!A3 -> 2 | B3: =Raw_Data!B3 -> 45302 | C3: =Raw_Data!C3 -> EU | D3: =Raw_Data!D3 -> Software | E3: =Raw_Data!E3 -> SMB | F3: =Raw_Data!F3 -> Partner | G3: =Raw_Data!G3 -> 122 | H3: =Raw_Data!H3 -> 399.65 | ... J3: =Raw_Data!J3 -> 19302.84 | K3: =TEXT(B3,"yyyy-mm") -> 2024-01 | L3: ="Q"&ROUNDUP(MONTH(B3)/3,0)&"-"&YEAR(B3) -> Q1-2024 | M3: =I3-J3 -> 29454.46 | N3: =IFERROR(M3/I3,0) -> 0.60410359
A4: =Raw_Data!A4 -> 3 | B4: =Raw_Data!B4 -> 45304 | C4: =Raw_Data!C4 -> UK | D4: =Raw_Data!D4 -> Software | E4: =Raw_Data!E4 -> Mid-Market | F4: =Raw_Data!F4 -> Online | G4: =Raw_Data!G4 -> 175 | H4: =Raw_Data!H4 -> 439.79 | ... J4: =Raw_Data!J4 -> 30325.14 | K4: =TEXT(B4,"yyyy-mm") -> 2024-01 | L4: ="Q"&ROUNDUP(MONTH(B4)/3,0)&"-"&YEAR(B4) -> Q1-2024 | M4: =I4-J4 -> 46638.11 | N4: =IFERROR(M4/I4,0) -> 0.60597896
A5: =Raw_Data!A5 -> 4 | B5: =Raw_Data!B5 -> 45308 | C5: =Raw_Data!C5 -> APAC | D5: =Raw_Data!D5 -> Software | E5: =Raw_Data!E5 -> Mid-Market | F5: =Raw_Data!F5 -> Direct | G5: =Raw_Data!G5 -> 157 | H5: =Raw_Data!H5 -> 423.5 | ... J5: =Raw_Data!J5 -> 27182.54 | K5: =TEXT(B5,"yyyy-mm") -> 2024-01 | L5: ="Q"&ROUNDUP(MONTH(B5)/3,0)&"-"&YEAR(B5) -> Q1-2024 | M5: =I5-J5 -> 39306.96 | N5: =IFERROR(M5/I5,0) -> 0.59117545
A6: =Raw_Data!A6 -> 5 | B6: =Raw_Data!B6 -> 45308 | C6: =Raw_Data!C6 -> UK | D6: =Raw_Data!D6 -> Hardware | E6: =Raw_Data!E6 -> Mid-Market | F6: =Raw_Data!F6 -> Direct | G6: =Raw_Data!G6 -> 163 | H6: =Raw_Data!H6 -> 532.96 | ... J6: =Raw_Data!J6 -> 57527.97 | K6: =TEXT(B6,"yyyy-mm") -> 2024-01 | L6: ="Q"&ROUNDUP(MONTH(B6)/3,0)&"-"&YEAR(B6) -> Q1-2024 | M6: =I6-J6 -> 29344.51 | N6: =IFERROR(M6/I6,0) -> 0.33778833
A7: =Raw_Data!A7 -> 6 | B7: =Raw_Data!B7 -> 45310 | C7: =Raw_Data!C7 -> UK | D7: =Raw_Data!D7 -> Software | E7: =Raw_Data!E7 -> Mid-Market | F7: =Raw_Data!F7 -> Partner | G7: =Raw_Data!G7 -> 189 | H7: =Raw_Data!H7 -> 437.94 | ... J7: =Raw_Data!J7 -> 36462.12 | K7: =TEXT(B7,"yyyy-mm") -> 2024-01 | L7: ="Q"&ROUNDUP(MONTH(B7)/3,0)&"-"&YEAR(B7) -> Q1-2024 | M7: =I7-J7 -> 46308.54 | N7: =IFERROR(M7/I7,0) -> 0.55948013
A8: =Raw_Data!A8 -> 7 | B8: =Raw_Data!B8 -> 45316 | C8: =Raw_Data!C8 -> APAC | D8: =Raw_Data!D8 -> Hardware | E8: =Raw_Data!E8 -> Enterprise | F8: =Raw_Data!F8 -> Direct | G8: =Raw_Data!G8 -> 218 | H8: =Raw_Data!H8 -> 606.71 | ... J8: =Raw_Data!J8 -> 92675.07 | K8: =TEXT(B8,"yyyy-mm") -> 2024-01 | L8: ="Q"&ROUNDUP(MONTH(B8)/3,0)&"-"&YEAR(B8) -> Q1-2024 | M8: =I8-J8 -> 39587.71 | N8: =IFERROR(M8/I8,0) -> 0.29931104
A9: =Raw_Data!A9 -> 8 | B9: =Raw_Data!B9 -> 45316 | C9: =Raw_Data!C9 -> US | D9: =Raw_Data!D9 -> Training | E9: =Raw_Data!E9 -> Enterprise | F9: =Raw_Data!F9 -> Online | G9: =Raw_Data!G9 -> 129 | H9: =Raw_Data!H9 -> 281.49 | ... J9: =Raw_Data!J9 -> 18653.99 | K9: =TEXT(B9,"yyyy-mm") -> 2024-01 | L9: ="Q"&ROUNDUP(MONTH(B9)/3,0)&"-"&YEAR(B9) -> Q1-2024 | M9: =I9-J9 -> 17658.22 | N9: =IFERROR(M9/I9,0) -> 0.48628877
A10: =Raw_Data!A10 -> 9 | B10: =Raw_Data!B10 -> 45319 | C10: =Raw_Data!C10 -> APAC | D10: =Raw_Data!D10 -> Services | E10: =Raw_Data!E10 -> Enterprise | F10: =Raw_Data!F10 -> Direct | G10: =Raw_Data!G10 -> 140 | H10: =Raw_Data!H10 -> 372.97 | ... J10: =Raw_Data!J10 -> 30417.33 | K10: =TEXT(B10,"yyyy-mm") -> 2024-01 | L10: ="Q"&ROUNDUP(MONTH(B10)/3,0)&"-"&YEAR(B10) -> Q1-2024 | M10: =I10-J10 -> 21798.47 | N10: =IFERROR(M10/I10,0) -> 0.41746885
A11: =Raw_Data!A11 -> 10 | B11: =Raw_Data!B11 -> 45322 | C11: =Raw_Data!C11 -> US | D11: =Raw_Data!D11 -> Hardware | E11: =Raw_Data!E11 -> Enterprise | F11: =Raw_Data!F11 -> Online | G11: =Raw_Data!G11 -> 142 | H11: =Raw_Data!H11 -> 778.96 | ... J11: =Raw_Data!J11 -> 75178.03 | K11: =TEXT(B11,"yyyy-mm") -> 2024-01 | L11: ="Q"&ROUNDUP(MONTH(B11)/3,0)&"-"&YEAR(B11) -> Q1-2024 | M11: =I11-J11 -> 35434.29 | N11: =IFERROR(M11/I11,0) -> 0.32034668
A12: =Raw_Data!A12 -> 11 | B12: =Raw_Data!B12 -> 45325 | C12: =Raw_Data!C12 -> US | D12: =Raw_Data!D12 -> Training | E12: =Raw_Data!E12 -> SMB | F12: =Raw_Data!F12 -> Direct | G12: =Raw_Data!G12 -> 202 | H12: =Raw_Data!H12 -> 218.22 | ... J12: =Raw_Data!J12 -> 21690.37 | K12: =TEXT(B12,"yyyy-mm") -> 2024-02 | L12: ="Q"&ROUNDUP(MONTH(B12)/3,0)&"-"&YEAR(B12) -> Q1-2024 | M12: =I12-J12 -> 22390.07 | N12: =IFERROR(M12/I12,0) -> 0.50793663
A13: =Raw_Data!A13 -> 12 | B13: =Raw_Data!B13 -> 45331 | C13: =Raw_Data!C13 -> US | D13: =Raw_Data!D13 -> Training | E13: =Raw_Data!E13 -> Enterprise | F13: =Raw_Data!F13 -> Direct | G13: =Raw_Data!G13 -> 133 | H13: =Raw_Data!H13 -> 292.07 | ... J13: =Raw_Data!J13 -> 19022.93 | K13: =TEXT(B13,"yyyy-mm") -> 2024-02 | L13: ="Q"&ROUNDUP(MONTH(B13)/3,0)&"-"&YEAR(B13) -> Q1-2024 | M13: =I13-J13 -> 19822.38 | N13: =IFERROR(M13/I13,0) -> 0.51029017
... A289: =Raw_Data!A289 -> 288 | B289: =Raw_Data!B289 -> 46159 | C289: =Raw_Data!C289 -> US | D289: =Raw_Data!D289 -> Training | E289: =Raw_Data!E289 -> Public Sector | F289: =Raw_Data!F289 -> Partner | G289: =Raw_Data!G289 -> 22 | H289: =Raw_Data!H289 -> 240.21 | ... J289: =Raw_Data!J289 -> 2454.19 | K289: =TEXT(B289,"yyyy-mm") -> 2026-05 | L289: ="Q"&ROUNDUP(MONTH(B289)/3,0)&"-"&YEAR(B289) -> Q2-2026 | M289: =I289-J289 -> 2830.43 | N289: =IFERROR(M289/I289,0) -> 0.53559764

Sheet KPIs
A1: Business Performance & Forecasting Analysis
A3: Metric | B3: Value | D3: Analyst Notes
A4: Total Revenue | B4: =SUM(Data_Cleaning!I2:I289) -> 13498422 | D4: This workbook simulates the type of performance analysis done by business, financial, and data analysts.
A5: Total Cost | B5: =SUM(Data_Cleaning!J2:J289) -> 7390371.6 | D5: Use the Scenario_Model sheet to test cost inflation and demand growth assumptions.
A6: Total Profit | B6: =SUM(Data_Cleaning!M2:M289) -> 6108050.5 | D6: Use the Dashboard sheet for the executive summary and visuals.
A7: Average Profit Margin | B7: =AVERAGE(Data_Cleaning!N2:N289) -> 0.47044915
A8: Transactions | B8: =COUNTA(Data_Cleaning!A2:A289) -> 288
A9: Average Revenue per Transaction | B9: =AVERAGE(Data_Cleaning!I2:I289) -> 46869.521
A10: Best Region by Profit | B10: =INDEX(Lists!A1:A4,MATCH(MAX(Analysis!H4:H7),Analysis!H4:H7,0)) -> EU

Sheet Analysis
A1: Analysis Tables
A3: Month | B3: Revenue | C3: Profit | E3: Region | F3: Revenue | G3: Cost | H3: Profit | I3: Avg Margin | J3: Transactions
A4: 2024-01 | B4: =SUMIF(Data_Cleaning!K:K,A4,Data_Cleaning!I:I) -> 719581.18 | C4: =SUMIF(Data_Cleaning!K:K,A4,Data_Cleaning!M:M) -> 319012.74 | E4: UK | F4: =SUMIF(Data_Cleaning!C:C,E4,Data_Cleaning!I:I) -> 3652755.9 | G4: =SUMIF(Data_Cleaning!C:C,E4,Data_Cleaning!J:J) -> 2001262.9 | H4: =SUMIF(Data_Cleaning!C:C,E4,Data_Cleaning!M:M) -> 1651493 | I4: =IFERROR(H4/F4,0) -> 0.45212248 | J4: =COUNTIF(Data_Cleaning!C:C,E4) -> 70
A5: 2024-02 | B5: =SUMIF(Data_Cleaning!K:K,A5,Data_Cleaning!I:I) -> 369294.8 | C5: =SUMIF(Data_Cleaning!K:K,A5,Data_Cleaning!M:M) -> 178770.79 | E5: EU | F5: =SUMIF(Data_Cleaning!C:C,E5,Data_Cleaning!I:I) -> 3964741.8 | G5: =SUMIF(Data_Cleaning!C:C,E5,Data_Cleaning!J:J) -> 2170529.7 | H5: =SUMIF(Data_Cleaning!C:C,E5,Data_Cleaning!M:M) -> 1794212.1 | I5: =IFERROR(H5/F5,0) -> 0.45254198 | J5: =COUNTIF(Data_Cleaning!C:C,E5) -> 83
A6: 2024-03 | B6: =SUMIF(Data_Cleaning!K:K,A6,Data_Cleaning!I:I) -> 536659.86 | C6: =SUMIF(Data_Cleaning!K:K,A6,Data_Cleaning!M:M) -> 251595.25 | E6: US | F6: =SUMIF(Data_Cleaning!C:C,E6,Data_Cleaning!I:I) -> 3324522.8 | G6: =SUMIF(Data_Cleaning!C:C,E6,Data_Cleaning!J:J) -> 1812499.3 | H6: =SUMIF(Data_Cleaning!C:C,E6,Data_Cleaning!M:M) -> 1512023.5 | I6: =IFERROR(H6/F6,0) -> 0.45480918 | J6: =COUNTIF(Data_Cleaning!C:C,E6) -> 72
A7: 2024-04 | B7: =SUMIF(Data_Cleaning!K:K,A7,Data_Cleaning!I:I) -> 387342.67 | C7: =SUMIF(Data_Cleaning!K:K,A7,Data_Cleaning!M:M) -> 165307.96 | E7: APAC | F7: =SUMIF(Data_Cleaning!C:C,E7,Data_Cleaning!I:I) -> 2556401.6 | G7: =SUMIF(Data_Cleaning!C:C,E7,Data_Cleaning!J:J) -> 1406079.7 | H7: =SUMIF(Data_Cleaning!C:C,E7,Data_Cleaning!M:M) -> 1150321.9 | I7: =IFERROR(H7/F7,0) -> 0.449977 | J7: =COUNTIF(Data_Cleaning!C:C,E7) -> 63
A8: 2024-05 | B8: =SUMIF(Data_Cleaning!K:K,A8,Data_Cleaning!I:I) -> 447343.82 | C8: =SUMIF(Data_Cleaning!K:K,A8,Data_Cleaning!M:M) -> 196156.04
A9: 2024-06 | B9: =SUMIF(Data_Cleaning!K:K,A9,Data_Cleaning!I:I) -> 397700.41 | C9: =SUMIF(Data_Cleaning!K:K,A9,Data_Cleaning!M:M) -> 179423.12
A10: 2024-07 | B10: =SUMIF(Data_Cleaning!K:K,A10,Data_Cleaning!I:I) -> 330833.76 | C10: =SUMIF(Data_Cleaning!K:K,A10,Data_Cleaning!M:M) -> 156613.19 | E10: Product | F10: Revenue | G10: Profit | H10: Avg Margin | I10: Transactions
A11: 2024-08 | B11: =SUMIF(Data_Cleaning!K:K,A11,Data_Cleaning!I:I) -> 451260.22 | C11: =SUMIF(Data_Cleaning!K:K,A11,Data_Cleaning!M:M) -> 163218.08 | E11: Software | F11: =SUMIF(Data_Cleaning!D:D,E11,Data_Cleaning!I:I) -> 4195052.5 | G11: =SUMIF(Data_Cleaning!D:D,E11,Data_Cleaning!M:M) -> 2422822.7 | H11: =IFERROR(G11/F11,0) -> 0.57754287 | I11: =COUNTIF(Data_Cleaning!D:D,E11) -> 77
A12: 2024-09 | B12: =SUMIF(Data_Cleaning!K:K,A12,Data_Cleaning!I:I) -> 557545.49 | C12: =SUMIF(Data_Cleaning!K:K,A12,Data_Cleaning!M:M) -> 254601.56 | E12: Services | F12: =SUMIF(Data_Cleaning!D:D,E12,Data_Cleaning!I:I) -> 3236015.2 | G12: =SUMIF(Data_Cleaning!D:D,E12,Data_Cleaning!M:M) -> 1456092.8 | H12: =IFERROR(G12/F12,0) -> 0.44996477 | I12: =COUNTIF(Data_Cleaning!D:D,E12) -> 71
A13: 2024-10 | B13: =SUMIF(Data_Cleaning!K:K,A13,Data_Cleaning!I:I) -> 531806.72 | C13: =SUMIF(Data_Cleaning!K:K,A13,Data_Cleaning!M:M) -> 239006.09 | E13: Hardware | F13: =SUMIF(Data_Cleaning!D:D,E13,Data_Cleaning!I:I) -> 4575535.5 | G13: =SUMIF(Data_Cleaning!D:D,E13,Data_Cleaning!M:M) -> 1457441.5 | H13: =IFERROR(G13/F13,0) -> 0.31852917 | I13: =COUNTIF(Data_Cleaning!D:D,E13) -> 67
A14: 2024-11 | B14: =SUMIF(Data_Cleaning!K:K,A14,Data_Cleaning!I:I) -> 386851.62 | C14: =SUMIF(Data_Cleaning!K:K,A14,Data_Cleaning!M:M) -> 163526.22 | E14: Training | F14: =SUMIF(Data_Cleaning!D:D,E14,Data_Cleaning!I:I) -> 1491818.9 | G14: =SUMIF(Data_Cleaning!D:D,E14,Data_Cleaning!M:M) -> 771693.53 | H14: =IFERROR(G14/F14,0) -> 0.51728366 | I14: =COUNTIF(Data_Cleaning!D:D,E14) -> 73
A15: 2024-12 | B15: =SUMIF(Data_Cleaning!K:K,A15,Data_Cleaning!I:I) -> 363049.29 | C15: =SUMIF(Data_Cleaning!K:K,A15,Data_Cleaning!M:M) -> 146658.93
A16: 2025-01 | B16: =SUMIF(Data_Cleaning!K:K,A16,Data_Cleaning!I:I) -> 523276.04 | C16: =SUMIF(Data_Cleaning!K:K,A16,Data_Cleaning!M:M) -> 262399.25
A17: 2025-02 | B17: =SUMIF(Data_Cleaning!K:K,A17,Data_Cleaning!I:I) -> 396344.42 | C17: =SUMIF(Data_Cleaning!K:K,A17,Data_Cleaning!M:M) -> 204069.28
A18: 2025-03 | B18: =SUMIF(Data_Cleaning!K:K,A18,Data_Cleaning!I:I) -> 470290.21 | C18: =SUMIF(Data_Cleaning!K:K,A18,Data_Cleaning!M:M) -> 254994.9
A19: 2025-04 | B19: =SUMIF(Data_Cleaning!K:K,A19,Data_Cleaning!I:I) -> 487405.47 | C19: =SUMIF(Data_Cleaning!K:K,A19,Data_Cleaning!M:M) -> 206016.21
A20: 2025-05 | B20: =SUMIF(Data_Cleaning!K:K,A20,Data_Cleaning!I:I) -> 564484.42 | C20: =SUMIF(Data_Cleaning!K:K,A20,Data_Cleaning!M:M) -> 242733.92
A21: 2025-06 | B21: =SUMIF(Data_Cleaning!K:K,A21,Data_Cleaning!I:I) -> 590435.18 | C21: =SUMIF(Data_Cleaning!K:K,A21,Data_Cleaning!M:M) -> 237032.71
A22: 2025-07 | B22: =SUMIF(Data_Cleaning!K:K,A22,Data_Cleaning!I:I) -> 456417.35 | C22: =SUMIF(Data_Cleaning!K:K,A22,Data_Cleaning!M:M) -> 197018.9
A23: 2025-08 | B23: =SUMIF(Data_Cleaning!K:K,A23,Data_Cleaning!I:I) -> 411100.58 | C23: =SUMIF(Data_Cleaning!K:K,A23,Data_Cleaning!M:M) -> 177194.8
A24: 2025-09 | B24: =SUMIF(Data_Cleaning!K:K,A24,Data_Cleaning!I:I) -> 418960.31 | C24: =SUMIF(Data_Cleaning!K:K,A24,Data_Cleaning!M:M) -> 185753.83
A25: 2025-10 | B25: =SUMIF(Data_Cleaning!K:K,A25,Data_Cleaning!I:I) -> 454237.32 | C25: =SUMIF(Data_Cleaning!K:K,A25,Data_Cleaning!M:M) -> 222383.97
A26: 2025-11 | B26: =SUMIF(Data_Cleaning!K:K,A26,Data_Cleaning!I:I) -> 411871.53 | C26: =SUMIF(Data_Cleaning!K:K,A26,Data_Cleaning!M:M) -> 227509.17
A27: 2025-12 | B27: =SUMIF(Data_Cleaning!K:K,A27,Data_Cleaning!I:I) -> 723075.31 | C27: =SUMIF(Data_Cleaning!K:K,A27,Data_Cleaning!M:M) -> 299391.51

Sheet Forecast
A1: Revenue Forecast
A2: Forecast uses a 3-month moving average; first two rows use startup values so the table has no visual gaps.
A3: Month | B3: Actual Revenue | C3: 3-Month Avg / Forecast | D3: Forecast Flag
A4: 2024-01 | B4: =Analysis!B4 -> 719581.18 | C4: =B4 -> 719581.18 | D4: Actual
A5: 2024-02 | B5: =Analysis!B5 -> 369294.8 | C5: =AVERAGE(B4:B5) -> 544437.99 | D5: Actual
A6: 2024-03 | B6: =Analysis!B6 -> 536659.86 | C6: =AVERAGE(B4:B6) -> 541845.28 | D6: Actual
A7: 2024-04 | B7: =Analysis!B7 -> 387342.67 | C7: =AVERAGE(B5:B7) -> 431099.11 | D7: Actual
A8: 2024-05 | B8: =Analysis!B8 -> 447343.82 | C8: =AVERAGE(B6:B8) -> 457115.45 | D8: Actual
A9: 2024-06 | B9: =Analysis!B9 -> 397700.41 | C9: =AVERAGE(B7:B9) -> 410795.63 | D9: Actual
A10: 2024-07 | B10: =Analysis!B10 -> 330833.76 | C10: =AVERAGE(B8:B10) -> 391959.33 | D10: Actual
A11: 2024-08 | B11: =Analysis!B11 -> 451260.22 | C11: =AVERAGE(B9:B11) -> 393264.8 | D11: Actual
A12: 2024-09 | B12: =Analysis!B12 -> 557545.49 | C12: =AVERAGE(B10:B12) -> 446546.49 | D12: Actual
A13: 2024-10 | B13: =Analysis!B13 -> 531806.72 | C13: =AVERAGE(B11:B13) -> 513537.48 | D13: Actual
A14: 2024-11 | B14: =Analysis!B14 -> 386851.62 | C14: =AVERAGE(B12:B14) -> 492067.94 | D14: Actual
A15: 2024-12 | B15: =Analysis!B15 -> 363049.29 | C15: =AVERAGE(B13:B15) -> 427235.88 | D15: Actual
A16: 2025-01 | B16: =Analysis!B16 -> 523276.04 | C16: =AVERAGE(B14:B16) -> 424392.32 | D16: Actual
A17: 2025-02 | B17: =Analysis!B17 -> 396344.42 | C17: =AVERAGE(B15:B17) -> 427556.58 | D17: Actual
... A27: 2025-12 | B27: =Analysis!B27 -> 723075.31 | C27: =AVERAGE(B25:B27) -> 529728.05 | D27: Actual
A28: 2026-01 | C28: =AVERAGE(B25:B27) -> 529728.05 | D28: Forecast
A29: 2026-02 | C29: =AVERAGE(B26:B27,C28) -> 554891.63 | D29: Forecast
A30: 2026-03 | C30: =AVERAGE(B27,C28:C29) -> 602565 | D30: Forecast
A31: 2026-04 | C31: =AVERAGE(C28:C30) -> 562394.89 | D31: Forecast
A32: 2026-05 | C32: =AVERAGE(C29:C31) -> 573283.84 | D32: Forecast
A33: 2026-06 | C33: =AVERAGE(C30:C32) -> 579414.58 | D33: Forecast

Sheet Scenario_Model
A1: Scenario Model
A2: Adjust demand and cost assumptions to test projected profitability.
A3: Inputs | D3: Projected Output
A4: Base Revenue | B4: =KPIs!B4 -> 13498422 | D4: Projected Revenue | E4: =B4*(1+B6) -> 14578296
A5: Base Cost | B5: =KPIs!B5 -> 7390371.6 | D5: Projected Cost | E5: =B5*(1+B7) -> 7759890.1
A6: Demand Growth % | B6: 0.08 | D6: Projected Profit | E6: =E4-E5 -> 6818405.7
A7: Cost Increase % | B7: 0.05 | D7: Projected Margin | E7: =IFERROR(E6/E4,0) -> 0.46770938

Sheet Dashboard
A1: Executive Dashboard
A2: Business performance snapshot covering revenue, profitability, and forward-looking forecast metrics.
A4: Total Revenue | D4: Total Profit | G4: Avg Margin | J4: Transactions
A5: =KPIs!B4 -> 13498422 | D5: =KPIs!B6 -> 6108050.5 | G5: =KPIs!B7 -> 0.47044915 | J5: =KPIs!B8 -> 288
A8: Monthly Performance | E8: Regional Performance | I8: 6-Month Forecast
A9: Month | B9: Revenue | C9: Profit | E9: Region | F9: Revenue | G9: Profit | I9: Future Month | J9: Forecast Revenue
A10: =Analysis!A4 -> 2024-01 | B10: =Analysis!B4 -> 719581.18 | C10: =Analysis!C4 -> 319012.74 | E10: =Analysis!E4 -> UK | F10: =Analysis!F4 -> 3652755.9 | G10: =Analysis!H4 -> 1651493 | I10: =Forecast!A28 -> 2026-01 | J10: =Forecast!B28 -> 0
A11: =Analysis!A5 -> 2024-02 | B11: =Analysis!B5 -> 369294.8 | C11: =Analysis!C5 -> 178770.79 | E11: =Analysis!E5 -> EU | F11: =Analysis!F5 -> 3964741.8 | G11: =Analysis!H5 -> 1794212.1 | I11: =Forecast!A29 -> 2026-02 | J11: =Forecast!B29 -> 0
A12: =Analysis!A6 -> 2024-03 | B12: =Analysis!B6 -> 536659.86 | C12: =Analysis!C6 -> 251595.25 | E12: =Analysis!E6 -> US | F12: =Analysis!F6 -> 3324522.8 | G12: =Analysis!H6 -> 1512023.5 | I12: =Forecast!A30 -> 2026-03 | J12: =Forecast!B30 -> 0
A13: =Analysis!A7 -> 2024-04 | B13: =Analysis!B7 -> 387342.67 | C13: =Analysis!C7 -> 165307.96 | E13: =Analysis!E7 -> APAC | F13: =Analysis!F7 -> 2556401.6 | G13: =Analysis!H7 -> 1150321.9 | I13: =Forecast!A31 -> 2026-04 | J13: =Forecast!B31 -> 0
A14: =Analysis!A8 -> 2024-05 | B14: =Analysis!B8 -> 447343.82 | C14: =Analysis!C8 -> 196156.04 | I14: =Forecast!A32 -> 2026-05 | J14: =Forecast!B32 -> 0
A15: =Analysis!A9 -> 2024-06 | B15: =Analysis!B9 -> 397700.41 | C15: =Analysis!C9 -> 179423.12 | I15: =Forecast!A33 -> 2026-06 | J15: =Forecast!B33 -> 0
A16: =Analysis!A10 -> 2024-07 | B16: =Analysis!B10 -> 330833.76 | C16: =Analysis!C10 -> 156613.19
A17: =Analysis!A11 -> 2024-08 | B17: =Analysis!B11 -> 451260.22 | C17: =Analysis!C11 -> 163218.08
A18: =Analysis!A12 -> 2024-09 | B18: =Analysis!B12 -> 557545.49 | C18: =Analysis!C12 -> 254601.56
A19: =Analysis!A13 -> 2024-10 | B19: =Analysis!B13 -> 531806.72 | C19: =Analysis!C13 -> 239006.09
A20: =Analysis!A14 -> 2024-11 | B20: =Analysis!B14 -> 386851.62 | C20: =Analysis!C14 -> 163526.22
A21: =Analysis!A15 -> 2024-12 | B21: =Analysis!B15 -> 363049.29 | C21: =Analysis!C15 -> 146658.93

Sheet Lists
A1: UK | B1: Software | C1: SMB | D1: Direct | E1: Theme
A2: EU | B2: Services | C2: Mid-Market | D2: Partner | E2: Navy
A3: US | B3: Hardware | C3: Enterprise | D3: Online | E3: Slate
A4: APAC | B4: Training | C4: Public Sector | E4: Teal
